Workbook

Sheet Assumptions
A1: ASML DCF — assumptions
A2: EVERY yellow cell is a judgement, not a fact. The defaults below are anchored starting points — read each one, change it if you disagree, and write your own reason in column D. Column D is the project; the arithmetic is not.
A4: Assumption | B4: Value | C4: Anchor / where the default comes from | D4: YOUR reasoning — fill this in
A5: REVENUE
A6: 2026 total net sales (€m) | B6: 44000 | C6: Guidance €43–45bn (Q2 2026 press release). This is the midpoint.
A7: Revenue growth 2027 | B7: 0.15 | C7: Capacity +30% planned for 2027. Judgement.
A8: Revenue growth 2028 | B8: 0.1 | C8: Judgement — deceleration assumed.
A9: Revenue growth 2029 | B9: 0.07 | C9: Judgement.
A10: Revenue growth 2030 | B10: 0.05 | C10: Judgement — maturing toward terminal.
A11: COSTS
A12: Gross margin (2026 onward) | B12: 0.55 | C12: Guidance 54–56% for 2026. 2025 actual 52.8%.
A13: R&D growth p.a. | B13: 0.08 | C13: Modelled as committed spend that grows, NOT as % of sales — that is what creates operating leverage.
A14: SG&A growth p.a. | B14: 0.08 | C14: Same logic as R&D.
A15: Effective tax rate | B15: 0.175 | C15: 17.7% in 2025; recent quarters ~17.5%.
A16: CASH
A17: D&A as % of sales | B17: 0.03 | C17: 3y average 3.0%.
A18: Capex as % of sales | B18: 0.06 | C18: 2025 trough 4.8%, 2023 peak 7.8%. Capacity is being expanded 30%, so a trough level is unlikely to hold.
A19: Working capital as % of revenue INCREASE | B19: 0.1 | C19: Crude. Customer prepayments (contract liabilities) partly fund growth, so this may be too high.
A20: DISCOUNT RATE
A21: Risk-free rate | B21: 0.0358 | C21: German 10y Bund, 15 Sep 2026.
A22: Equity risk premium | B22: 0.05 | C22: Replace with Damodaran's current implied ERP and cite it.
A23: Beta (adjusted) | B23: 1.45 | C23: Your own regression: 5y weekly vs STOXX Europe 600, Blume-adjusted. Range across indices 1.26–1.66.
A24: Cost of debt (pre-tax) | B24: 0.03 | C24: Interest paid €114.5m on ~€4.4bn debt. Barely matters — see below.
A25: Total debt (€m) | B25: 4390.9 | C25: Short-term €1,681.9m + long-term €2,709.0m, AR2025 p.278.
A26: Market capitalisation (€m) | B26: 529600 | C26: $611.33bn ÷ 1.1543, 15 Sep 2026.
A27: Cost of equity | B27: =Assumptions!$B$21+Assumptions!$B$23*Assumptions!$B$22 -> 0.1083 | C27: CAPM: rf + beta x ERP
A28: WACC | B28: =(Assumptions!$B$26/(Assumptions!$B$26+Assumptions!$B$25))*Assumptions!$B$27+(Assumptions!$B$25/(Assumptions!$B$26+Assumptions!$B$25))*Assumptions!$B$24*(1-Assumptions!$B$15) -> 0.10761299 | C28: Debt is <1% of capital, so WACC is essentially the cost of equity.
A29: TERMINAL VALUE
A30: Terminal growth rate | B30: 0.02 | C30: Must be below long-run nominal GDP. Above 3% and you have assumed ASML becomes the world economy.
A31: MARKET DATA
A32: Net cash (€m) | B32: 8931 | C32: Cash €12,916.0m + ST investments €405.9m − total debt. ADDED to EV.
A33: Diluted shares (m) | B33: 384.9 | C33: Q2 2026 weighted average diluted.
A34: Share price (€) | B34: 1379 | C34: $1,591.48 ÷ 1.1543, close 15 Sep 2026.
A36: Before you use this model, change at least three of these and write why. A model whose assumptions you did not choose is not a project.

Sheet DCF
A1: ASML — discounted cash flow
A2: € millions. Black = formula. Green = from the Assumptions tab. Change nothing here; change Assumptions.
B4: 2025A | C4: 2026E | D4: 2027E | E4: 2028E | F4: 2029E | G4: 2030E
A5: Forecast period t | B5: 0 | C5: 1 | D5: 2 | E5: 3 | F5: 4 | G5: 5 | I5: used for discounting
A6: Total net sales | B6: =32667.3 -> 32667.3 | C6: =Assumptions!$B$6 -> 44000 | D6: =C6*(1+Assumptions!$B$7) -> 50600 | E6: =D6*(1+Assumptions!$B$8) -> 55660 | F6: =E6*(1+Assumptions!$B$9) -> 59556.2 | G6: =F6*(1+Assumptions!$B$10) -> 62534.01 | I6: 2025 actual, AR2025 p.276; 2026 from guidance
A7: growth % | C7: =C6/B6-1 -> 0.34691266 | D7: =D6/C6-1 -> 0.15 | E7: =E6/D6-1 -> 0.1 | F7: =F6/E6-1 -> 0.07 | G7: =G6/F6-1 -> 0.05
A8: Gross profit | C8: =C6*Assumptions!$B$12 -> 24200 | D8: =D6*Assumptions!$B$12 -> 27830 | E8: =E6*Assumptions!$B$12 -> 30613 | F8: =F6*Assumptions!$B$12 -> 32755.91 | G8: =G6*Assumptions!$B$12 -> 34393.705
A9: R&D costs | C9: =-4698.8*(1+Assumptions!$B$13)^1 -> -5074.704 | D9: =-4698.8*(1+Assumptions!$B$13)^2 -> -5480.6803 | E9: =-4698.8*(1+Assumptions!$B$13)^3 -> -5919.1347 | F9: =-4698.8*(1+Assumptions!$B$13)^4 -> -6392.6655 | G9: =-4698.8*(1+Assumptions!$B$13)^5 -> -6904.0788 | I9: 2025 actual €4,698.8m grown forward
A10: SG&A costs | C10: =-1257.8*(1+Assumptions!$B$14)^1 -> -1358.424 | D10: =-1257.8*(1+Assumptions!$B$14)^2 -> -1467.0979 | E10: =-1257.8*(1+Assumptions!$B$14)^3 -> -1584.4658 | F10: =-1257.8*(1+Assumptions!$B$14)^4 -> -1711.223 | G10: =-1257.8*(1+Assumptions!$B$14)^5 -> -1848.1209 | I10: 2025 actual €1,257.8m grown forward
A11: EBIT | C11: =C8+C9+C10 -> 17766.872 | D11: =D8+D9+D10 -> 20882.222 | E11: =E8+E9+E10 -> 23109.4 | F11: =F8+F9+F10 -> 24652.021 | G11: =G8+G9+G10 -> 25641.506
A12: EBIT margin % | C12: =C11/C6 -> 0.40379255 | D12: =D11/D6 -> 0.41269213 | E12: =E11/E6 -> 0.41518864 | F12: =F11/F6 -> 0.41392872 | G12: =G11/G6 -> 0.41004097 | I12: rises with revenue because R&D does not track sales — that is operating leverage
A13: Tax on EBIT | C13: =-C11*Assumptions!$B$15 -> -3109.2026 | D13: =-D11*Assumptions!$B$15 -> -3654.3888 | E13: =-E11*Assumptions!$B$15 -> -4044.1449 | F13: =-F11*Assumptions!$B$15 -> -4314.1038 | G13: =-G11*Assumptions!$B$15 -> -4487.2635
A14: NOPAT | C14: =C11+C13 -> 14657.669 | D14: =D11+D13 -> 17227.833 | E14: =E11+E13 -> 19065.255 | F14: =F11+F13 -> 20337.918 | G14: =G11+G13 -> 21154.242
A15: add: D&A | C15: =C6*Assumptions!$B$17 -> 1320 | D15: =D6*Assumptions!$B$17 -> 1518 | E15: =E6*Assumptions!$B$17 -> 1669.8 | F15: =F6*Assumptions!$B$17 -> 1786.686 | G15: =G6*Assumptions!$B$17 -> 1876.0203
A16: less: capex | C16: =-C6*Assumptions!$B$18 -> -2640 | D16: =-D6*Assumptions!$B$18 -> -3036 | E16: =-E6*Assumptions!$B$18 -> -3339.6 | F16: =-F6*Assumptions!$B$18 -> -3573.372 | G16: =-G6*Assumptions!$B$18 -> -3752.0406
A17: less: working capital | C17: =-(C6-B6)*Assumptions!$B$19 -> -1133.27 | D17: =-(D6-C6)*Assumptions!$B$19 -> -660 | E17: =-(E6-D6)*Assumptions!$B$19 -> -506 | F17: =-(F6-E6)*Assumptions!$B$19 -> -389.62 | G17: =-(G6-F6)*Assumptions!$B$19 -> -297.781
A18: Free cash flow | C18: =C14+C15+C16+C17 -> 12204.399 | D18: =D14+D15+D16+D17 -> 15049.833 | E18: =E14+E15+E16+E17 -> 16889.455 | F18: =F14+F15+F16+F17 -> 18161.612 | G18: =G14+G15+G16+G17 -> 18980.441 | I18: NOPAT + D&A − capex − working capital
A19: Discount factor | C19: =1/(1+Assumptions!$B$28)^C5 -> 0.90284243 | D19: =1/(1+Assumptions!$B$28)^D5 -> 0.81512446 | E19: =1/(1+Assumptions!$B$28)^E5 -> 0.73592894 | F19: =1/(1+Assumptions!$B$28)^F5 -> 0.66442788 | G19: =1/(1+Assumptions!$B$28)^G5 -> 0.59987368
A20: PV of free cash flow | C20: =C18*C19 -> 11018.65 | D20: =D18*D19 -> 12267.487 | E20: =E18*E19 -> 12429.438 | F20: =F18*F19 -> 12067.081 | G20: =G18*G19 -> 11385.867
A22: VALUATION
A23: Sum of PV, 2026–30 | C23: =SUM(C20:G20) -> 59168.523
A24: Terminal value (2030, nominal) | C24: =G18*(1+Assumptions!$B$30)/(Assumptions!$B$28-Assumptions!$B$30) -> 220972.38 | I24: Gordon growth on 2030 free cash flow
A25: PV of terminal value | C25: =C24*G19 -> 132555.51
A26: Enterprise value | C26: =C23+C25 -> 191724.04
A27: Terminal value as % of EV | C27: =C25/C26 -> 0.69138704 | I27: if this is 70%+, the answer is mostly your terminal assumption
A28: add: net cash | C28: =Assumptions!$B$32 -> 8931 | I28: ASML has net CASH, so this is added, not subtracted
A29: Equity value | C29: =C26+Assumptions!$B$32 -> 200655.04
A30: Value per share (€) | C30: =C29/Assumptions!$B$33 -> 521.31732
A31: Market price (€) | C31: =Assumptions!$B$34 -> 1379
A32: Upside / (downside) | C32: =C30/Assumptions!$B$34-1 -> -0.62195988 | I32: your recommendation, in one cell
A34: REVERSE DCF — what is the market already assuming? | I34: Solve the model backwards: hold your forecast, find the terminal growth that equals today's price.
A35: Market enterprise value | C35: =Assumptions!$B$26-Assumptions!$B$32 -> 520669
A36: Implied PV of terminal value | C36: =C35-C23 -> 461500.48
A37: Implied terminal value (nominal) | C37: =C36/G19 -> 769329.43
A38: IMPLIED terminal growth rate | C38: =(C37*Assumptions!$B$28-G18)/(G18+C37) -> 0.08094456 | I38: compare with long-run nominal GDP of roughly 4%. This is the headline of your note.

Sheet Sensitivity
A1: Value per share (€) — WACC against terminal growth
A2: Each cell re-runs the whole valuation at that pair. Your base case is highlighted on the Assumptions tab.
A4: WACC ↓ g → | B4: 0.01 | C4: 0.015 | D4: 0.02 | E4: 0.025 | F4: 0.03
A5: 0.085 | B5: =(SUMPRODUCT(DCF!$C$18:$G$18,(1+$A5)^-DCF!$C$5:$G$5)+DCF!$G$18*(1+B$4)/($A5-B$4)/(1+$A5)^5+Assumptions!$B$32)/Assumptions!$B$33 -> 628.47997 | C5: =(SUMPRODUCT(DCF!$C$18:$G$18,(1+$A5)^-DCF!$C$5:$G$5)+DCF!$G$18*(1+C$4)/($A5-C$4)/(1+$A5)^5+Assumptions!$B$32)/Assumptions!$B$33 -> 662.3683 | D5: =(SUMPRODUCT(DCF!$C$18:$G$18,(1+$A5)^-DCF!$C$5:$G$5)+DCF!$G$18*(1+D$4)/($A5-D$4)/(1+$A5)^5+Assumptions!$B$32)/Assumptions!$B$33 -> 701.47021 | E5: =(SUMPRODUCT(DCF!$C$18:$G$18,(1+$A5)^-DCF!$C$5:$G$5)+DCF!$G$18*(1+E$4)/($A5-E$4)/(1+$A5)^5+Assumptions!$B$32)/Assumptions!$B$33 -> 747.08911 | F5: =(SUMPRODUCT(DCF!$C$18:$G$18,(1+$A5)^-DCF!$C$5:$G$5)+DCF!$G$18*(1+F$4)/($A5-F$4)/(1+$A5)^5+Assumptions!$B$32)/Assumptions!$B$33 -> 801.00236
A6: 0.095 | B6: =(SUMPRODUCT(DCF!$C$18:$G$18,(1+$A6)^-DCF!$C$5:$G$5)+DCF!$G$18*(1+B$4)/($A6-B$4)/(1+$A6)^5+Assumptions!$B$32)/Assumptions!$B$33 -> 554.54981 | C6: =(SUMPRODUCT(DCF!$C$18:$G$18,(1+$A6)^-DCF!$C$5:$G$5)+DCF!$G$18*(1+C$4)/($A6-C$4)/(1+$A6)^5+Assumptions!$B$32)/Assumptions!$B$33 -> 579.77085 | D6: =(SUMPRODUCT(DCF!$C$18:$G$18,(1+$A6)^-DCF!$C$5:$G$5)+DCF!$G$18*(1+D$4)/($A6-D$4)/(1+$A6)^5+Assumptions!$B$32)/Assumptions!$B$33 -> 608.3547 | E6: =(SUMPRODUCT(DCF!$C$18:$G$18,(1+$A6)^-DCF!$C$5:$G$5)+DCF!$G$18*(1+E$4)/($A6-E$4)/(1+$A6)^5+Assumptions!$B$32)/Assumptions!$B$33 -> 641.02195 | F6: =(SUMPRODUCT(DCF!$C$18:$G$18,(1+$A6)^-DCF!$C$5:$G$5)+DCF!$G$18*(1+F$4)/($A6-F$4)/(1+$A6)^5+Assumptions!$B$32)/Assumptions!$B$33 -> 678.71493
A7: 0.1076 | B7: =(SUMPRODUCT(DCF!$C$18:$G$18,(1+$A7)^-DCF!$C$5:$G$5)+DCF!$G$18*(1+B$4)/($A7-B$4)/(1+$A7)^5+Assumptions!$B$32)/Assumptions!$B$33 -> 483.06982 | C7: =(SUMPRODUCT(DCF!$C$18:$G$18,(1+$A7)^-DCF!$C$5:$G$5)+DCF!$G$18*(1+C$4)/($A7-C$4)/(1+$A7)^5+Assumptions!$B$32)/Assumptions!$B$33 -> 501.19724 | D7: =(SUMPRODUCT(DCF!$C$18:$G$18,(1+$A7)^-DCF!$C$5:$G$5)+DCF!$G$18*(1+D$4)/($A7-D$4)/(1+$A7)^5+Assumptions!$B$32)/Assumptions!$B$33 -> 521.39399 | E7: =(SUMPRODUCT(DCF!$C$18:$G$18,(1+$A7)^-DCF!$C$5:$G$5)+DCF!$G$18*(1+E$4)/($A7-E$4)/(1+$A7)^5+Assumptions!$B$32)/Assumptions!$B$33 -> 544.03587 | F7: =(SUMPRODUCT(DCF!$C$18:$G$18,(1+$A7)^-DCF!$C$5:$G$5)+DCF!$G$18*(1+F$4)/($A7-F$4)/(1+$A7)^5+Assumptions!$B$32)/Assumptions!$B$33 -> 569.59551
A8: 0.115 | B8: =(SUMPRODUCT(DCF!$C$18:$G$18,(1+$A8)^-DCF!$C$5:$G$5)+DCF!$G$18*(1+B$4)/($A8-B$4)/(1+$A8)^5+Assumptions!$B$32)/Assumptions!$B$33 -> 449.13297 | C8: =(SUMPRODUCT(DCF!$C$18:$G$18,(1+$A8)^-DCF!$C$5:$G$5)+DCF!$G$18*(1+C$4)/($A8-C$4)/(1+$A8)^5+Assumptions!$B$32)/Assumptions!$B$33 -> 464.32584 | D8: =(SUMPRODUCT(DCF!$C$18:$G$18,(1+$A8)^-DCF!$C$5:$G$5)+DCF!$G$18*(1+D$4)/($A8-D$4)/(1+$A8)^5+Assumptions!$B$32)/Assumptions!$B$33 -> 481.11795 | E8: =(SUMPRODUCT(DCF!$C$18:$G$18,(1+$A8)^-DCF!$C$5:$G$5)+DCF!$G$18*(1+E$4)/($A8-E$4)/(1+$A8)^5+Assumptions!$B$32)/Assumptions!$B$33 -> 499.77585 | F8: =(SUMPRODUCT(DCF!$C$18:$G$18,(1+$A8)^-DCF!$C$5:$G$5)+DCF!$G$18*(1+F$4)/($A8-F$4)/(1+$A8)^5+Assumptions!$B$32)/Assumptions!$B$33 -> 520.6288
A9: 0.125 | B9: =(SUMPRODUCT(DCF!$C$18:$G$18,(1+$A9)^-DCF!$C$5:$G$5)+DCF!$G$18*(1+B$4)/($A9-B$4)/(1+$A9)^5+Assumptions!$B$32)/Assumptions!$B$33 -> 410.25985 | C9: =(SUMPRODUCT(DCF!$C$18:$G$18,(1+$A9)^-DCF!$C$5:$G$5)+DCF!$G$18*(1+C$4)/($A9-C$4)/(1+$A9)^5+Assumptions!$B$32)/Assumptions!$B$33 -> 422.42809 | D9: =(SUMPRODUCT(DCF!$C$18:$G$18,(1+$A9)^-DCF!$C$5:$G$5)+DCF!$G$18*(1+D$4)/($A9-D$4)/(1+$A9)^5+Assumptions!$B$32)/Assumptions!$B$33 -> 435.75521 | E9: =(SUMPRODUCT(DCF!$C$18:$G$18,(1+$A9)^-DCF!$C$5:$G$5)+DCF!$G$18*(1+E$4)/($A9-E$4)/(1+$A9)^5+Assumptions!$B$32)/Assumptions!$B$33 -> 450.41504 | F9: =(SUMPRODUCT(DCF!$C$18:$G$18,(1+$A9)^-DCF!$C$5:$G$5)+DCF!$G$18*(1+F$4)/($A9-F$4)/(1+$A9)^5+Assumptions!$B$32)/Assumptions!$B$33 -> 466.61801
A11: Market price today (€) | B11: =Assumptions!$B$34 -> 1379
A12: Read it this way: if no pair in this grid reaches the market price, the market is not using a discounted cash flow at all — or is assuming growth your forecast does not contain.

Sheet Comps
A1: Trading comparables — the sanity check
A2: STALE: dated 8 May 2026, secondary source. Refresh before you use these, and add Tokyo Electron and ASM International.
A4: Company | B4: P/E | C4: P/S | D4: EV/EBITDA | E4: Market cap ($bn)
A5: ASML | B5: 56.8 | C5: 16.7 | D5: 43.8 | E5: 589.2
A6: Lam Research | B6: 53.7 | C6: 16.6 | D6: 45.7 | E6: 360
A7: Applied Materials | B7: 41.5 | C7: 11.5 | D7: 38.7 | E7: 325.6
A8: KLA | B8: 49.6 | C8: 17.7 | D8: 40.8 | E8: 231.5
A9: Tokyo Electron
A10: ASM International
A12: ASML's own implied multiples, from this model:
A13: EV / 2026E EBITDA | B13: =(Assumptions!$B$26-Assumptions!$B$32)/(DCF!C11+DCF!C15) -> 27.278907
A14: EV / 2026E sales | B14: =(Assumptions!$B$26-Assumptions!$B$32)/DCF!C6 -> 11.833386
A16: A monopoly deserves a premium to peers. Say how big a premium you think is justified, and why — that is the argument, not the table.

Sheet Sources
A1: Every hard number and where it came from
A3: Item | B3: Value | C3: Source | D3: Date
A4: 2025 total net sales | B4: €32,667.3m | C4: ASML Annual Report 2025 (US GAAP), p.276 | D4: FY2025
A5: 2025 gross profit | B5: €17,258.0m | C5: AR2025 p.276 | D5: FY2025
A6: 2025 R&D / SG&A | B6: €4,698.8m / €1,257.8m | C6: AR2025 p.276 | D6: FY2025
A7: 2025 D&A | B7: €1,025.9m | C7: AR2025 p.281 | D7: FY2025
A8: 2025 capex (PP&E) | B8: €1,573.6m | C8: AR2025 p.281 | D8: FY2025
A9: Cash + ST investments | B9: €13,321.9m | C9: AR2025 p.278 | D9: 31 Dec 2025
A10: Total debt | B10: €4,390.9m | C10: AR2025 p.278 | D10: 31 Dec 2025
A11: H1 2026 net sales | B11: €18,093.4m | C11: Q2 2026 quarterly summary (US GAAP) | D11: H1 2026
A12: Diluted shares | B12: 384.9m | C12: Q2 2026 quarterly summary | D12: Q2 2026
A13: FY2026 guidance | B13: €43–45bn, GM 54–56% | C13: ASML Q2 2026 press release | D13: 15 Jul 2026
A14: Q3 2026 guidance | B14: €11.0–12.0bn, GM 55–57% | C14: ASML Q2 2026 press release | D14: 15 Jul 2026
... A21: Peer multiples | B21: see Comps tab | C21: Secondary source — STALE, refresh | D21: 8 May 2026
